get_html_from_safari/__init__.py
get_html_from_safari/get_html.py
get_html_from_safari/get_html_from_safari.py
get_html_from_safari/applescripts/fetch_html.scpt
get_html_from_safari/applescripts/safari_activate.scpt
get_html_from_safari/applescripts/safari_grab_source.scpt
get_html_from_safari/applescripts/safari_has_windows.scpt
get_html_from_safari/applescripts/safari_is_running.scpt
get_html_from_safari/applescripts/safari_quit.scpt
get_html_from_safari/applescripts/safari_window_exists.scpt
get_html_from_safari-0.2.3.dist-info/AUTHORS.rst
get_html_from_safari-0.2.3.dist-info/LICENSE
get_html_from_safari-0.2.3.dist-info/METADATA
get_html_from_safari-0.2.3.dist-info/WHEEL
get_html_from_safari-0.2.3.dist-info/entry_points.txt
get_html_from_safari-0.2.3.dist-info/top_level.txt
get_html_from_safari-0.2.3.dist-info/RECORD
