Metadata-Version: 2.1
Name: get-html-from-safari
Version: 0.2.3
Summary: Get HTMl code from the Safari browser
Home-page: https://github.com/sdondley/get_html_from_safari
Author: Steve Dondley
Author-email: s@dondley.com
License: Apache Software License 2.0
Keywords: get_html_from_safari
Platform: MacOS
Classifier: Development Status :: 4 - Beta
Classifier: Intended Audience :: Developers
Classifier: License :: OSI Approved :: Apache Software License
Classifier: Natural Language :: English
Classifier: Operating System :: MacOS :: MacOS X
Classifier: Operating System :: MacOS
Classifier: Programming Language :: Python :: 3
Classifier: Programming Language :: Python :: 3.6
Classifier: Programming Language :: Python :: 3.7
Classifier: Programming Language :: Python :: 3.8
Requires-Python: >=3.6
License-File: LICENSE
License-File: AUTHORS.rst
